sphinx_govbr_theme/__init__.py
sphinx_govbr_theme/breadcrumbs.html
sphinx_govbr_theme/footer.html
sphinx_govbr_theme/header.html
sphinx_govbr_theme/layout.html
sphinx_govbr_theme/search.html
sphinx_govbr_theme/searchbox.html
sphinx_govbr_theme/theme.conf
sphinx_govbr_theme/versions.html
sphinx_govbr_theme/locale/sphinx.pot
sphinx_govbr_theme/locale/de/LC_MESSAGES/sphinx.mo
sphinx_govbr_theme/locale/de/LC_MESSAGES/sphinx.po
sphinx_govbr_theme/locale/en/LC_MESSAGES/sphinx.mo
sphinx_govbr_theme/locale/en/LC_MESSAGES/sphinx.po
sphinx_govbr_theme/locale/es/LC_MESSAGES/sphinx.mo
sphinx_govbr_theme/locale/es/LC_MESSAGES/sphinx.po
sphinx_govbr_theme/locale/et/LC_MESSAGES/sphinx.mo
sphinx_govbr_theme/locale/et/LC_MESSAGES/sphinx.po
sphinx_govbr_theme/locale/fa_IR/LC_MESSAGES/sphinx.mo
sphinx_govbr_theme/locale/fa_IR/LC_MESSAGES/sphinx.po
sphinx_govbr_theme/locale/fr/LC_MESSAGES/sphinx.mo
sphinx_govbr_theme/locale/fr/LC_MESSAGES/sphinx.po
sphinx_govbr_theme/locale/it/LC_MESSAGES/sphinx.mo
sphinx_govbr_theme/locale/it/LC_MESSAGES/sphinx.po
sphinx_govbr_theme/locale/lt/LC_MESSAGES/sphinx.mo
sphinx_govbr_theme/locale/lt/LC_MESSAGES/sphinx.po
sphinx_govbr_theme/locale/nl/LC_MESSAGES/sphinx.mo
sphinx_govbr_theme/locale/nl/LC_MESSAGES/sphinx.po
sphinx_govbr_theme/locale/pl/LC_MESSAGES/sphinx.mo
sphinx_govbr_theme/locale/pl/LC_MESSAGES/sphinx.po
sphinx_govbr_theme/locale/pt/LC_MESSAGES/sphinx.mo
sphinx_govbr_theme/locale/pt/LC_MESSAGES/sphinx.po
sphinx_govbr_theme/locale/pt_BR/LC_MESSAGES/sphinx.mo
sphinx_govbr_theme/locale/pt_BR/LC_MESSAGES/sphinx.po
sphinx_govbr_theme/locale/ru/LC_MESSAGES/sphinx.mo
sphinx_govbr_theme/locale/ru/LC_MESSAGES/sphinx.po
sphinx_govbr_theme/locale/sv/LC_MESSAGES/sphinx.mo
sphinx_govbr_theme/locale/sv/LC_MESSAGES/sphinx.po
sphinx_govbr_theme/locale/tr/LC_MESSAGES/sphinx.mo
sphinx_govbr_theme/locale/tr/LC_MESSAGES/sphinx.po
sphinx_govbr_theme/locale/zh_CN/LC_MESSAGES/sphinx.mo
sphinx_govbr_theme/locale/zh_CN/LC_MESSAGES/sphinx.po
sphinx_govbr_theme-1.0.4.dist-info/LICENSE
sphinx_govbr_theme-1.0.4.dist-info/METADATA
sphinx_govbr_theme-1.0.4.dist-info/WHEEL
sphinx_govbr_theme-1.0.4.dist-info/entry_points.txt
sphinx_govbr_theme-1.0.4.dist-info/top_level.txt
sphinx_govbr_theme-1.0.4.dist-info/RECORD
