Metadata-Version: 2.1
Name: sphinx-govbr-theme
Version: 1.0.4
Summary: Tema gov.br para Sphinx
Home-page: https://github.com/caduvieira/sphinx_govbr_theme
Author: Baseado no Read the Docs, Inc. & contributors
Author-email: dev@readthedocs.org
License: MIT
Project-URL: Homepage, https://sphinx-govbr-theme.readthedocs.io/
Project-URL: Source Code, https://github.com/caduvieira/sphinx_govbr_theme
Project-URL: Issue Tracker, https://github.com/caduvieira/sphinx_govbr_theme/issues
Platform: UNKNOWN
Classifier: Framework :: Sphinx
Classifier: Framework :: Sphinx :: Theme
Classifier: Development Status :: 5 - Production/Stable
Classifier: License :: OSI Approved :: MIT License
Classifier: Environment :: Console
Classifier: Environment :: Web Environment
Classifier: Intended Audience :: Developers
Classifier: Programming Language :: Python :: 2.7
Classifier: Programming Language :: Python :: 3
Classifier: Programming Language :: Python :: 3.6
Classifier: Programming Language :: Python :: 3.7
Classifier: Programming Language :: Python :: 3.8
Classifier: Programming Language :: Python :: 3.9
Classifier: Operating System :: OS Independent
Classifier: Topic :: Documentation
Classifier: Topic :: Software Development :: Documentation
Requires-Python: >=2.7,!=3.0.*,!=3.1.*,!=3.2.*,!=3.3.*
License-File: LICENSE
Requires-Dist: docutils (<0.18)
Requires-Dist: sphinx (>=1.6)
Provides-Extra: dev
Requires-Dist: bump2version ; extra == 'dev'
Requires-Dist: sphinxcontrib-httpdomain ; extra == 'dev'
Requires-Dist: transifex-client ; extra == 'dev'
